eliater/__init__.py
eliater/api.py
eliater/discover_latent_nodes.py
eliater/io.py
eliater/network_validation.py
eliater/py.typed
eliater/regression.py
eliater/version.py
eliater/data/EColi_obs_data.csv
eliater/data/__init__.py
eliater/data/cd3cd28+g0076.csv
eliater/data/cd3cd28.csv
eliater/data/cd3cd28.xls
eliater/data/sachs.data.csv
eliater/data/sachs_discretized_2bin.csv
eliater/examples/__init__.py
eliater/examples/ecoli.py
eliater/examples/multi_causal_path.py
eliater/examples/sars.py
eliater/examples/sars_cov2.py
eliater/examples/sars_cov2_discrete.py
eliater/examples/t_cell_signaling_pathway.py
eliater/examples/frontdoor_backdoor_discrete/__init__.py
eliater/examples/frontdoor_backdoor_discrete/example1.py
eliater/frontdoor_backdoor/__init__.py
eliater/frontdoor_backdoor/base.py
eliater/frontdoor_backdoor/example1.py
eliater/frontdoor_backdoor/example2.py
eliater/frontdoor_backdoor/example3.py
eliater/frontdoor_backdoor/motivating_example.py
eliater-0.0.2.dist-info/LICENSE
eliater-0.0.2.dist-info/METADATA
eliater-0.0.2.dist-info/WHEEL
eliater-0.0.2.dist-info/top_level.txt
eliater-0.0.2.dist-info/RECORD
