Metadata-Version: 2.1
Name: eliater
Version: 0.0.2
Summary: A high level, end-to-end causal inference workflow.
Home-page: https://github.com/y0-causal-inference/eliater
Download-URL: https://github.com/y0-causal-inference/eliater/releases
Author: Sara Taheri
Author-email: srtaheri66@gmail.com
Maintainer: Charles Tapley Hoyt
Maintainer-email: cthoyt@gmail.com
License: MIT
Project-URL: Tracker, https://github.com/y0-causal-inference/eliater/issues
Project-URL: Source, https://github.com/y0-causal-inference/eliater
Project-URL: Documentation, https://eliater.readthedocs.io
Keywords: snekpack,cookiecutter,causal inference
Classifier: Development Status :: 1 - Planning
Classifier: Environment :: Console
Classifier: Intended Audience :: Developers
Classifier: License :: OSI Approved :: MIT License
Classifier: Operating System :: OS Independent
Classifier: Framework :: Pytest
Classifier: Framework :: tox
Classifier: Framework :: Sphinx
Classifier: Programming Language :: Python
Classifier: Programming Language :: Python :: 3.10
Classifier: Programming Language :: Python :: 3.11
Classifier: Programming Language :: Python :: 3 :: Only
Requires-Python: >=3.10
License-File: LICENSE
Requires-Dist: y0 >=0.2.7
Requires-Dist: scipy
Requires-Dist: numpy
Requires-Dist: ananke-causal >=0.5.0
Requires-Dist: pgmpy >=0.1.24
Requires-Dist: matplotlib
Requires-Dist: pandas
Requires-Dist: seaborn
Requires-Dist: optimaladj >=0.0.4
Provides-Extra: docs
Requires-Dist: sphinx <7.0 ; extra == 'docs'
Requires-Dist: sphinx-rtd-theme ; extra == 'docs'
Requires-Dist: sphinx-automodapi ; extra == 'docs'
Requires-Dist: texext ; extra == 'docs'
Provides-Extra: tests
Requires-Dist: pytest ; extra == 'tests'
Requires-Dist: coverage ; extra == 'tests'
